classes/__init__.py
classes/nag.py
functions/__init__.py
functions/convert_bit_array_to_int.py
functions/convert_int_to_bit_array.py
functions/convert_json_to_nag.py
functions/convert_nag_networkx_to_graphviz.py
functions/convert_nag_to_json.py
functions/export_nag_to_pdf.py
functions/get_nag_function_number.py
functions/get_nag_function_type.py
functions/get_nag_sample.py
functions/load_nag.py
functions/nag_function_is_constant.py
functions/nag_function_is_input.py
functions/nag_function_is_nand.py
functions/nag_function_is_output.py
functions/plot_nag.py
functions/plot_nag_ett.py
functions/plot_nag_graph.py
functions/save_nag.py
functions/substitute_nag_function.py
functions/validate_nag_function_name.py
pyxag-0.0.3.dist-info/LICENSE
pyxag-0.0.3.dist-info/METADATA
pyxag-0.0.3.dist-info/WHEEL
pyxag-0.0.3.dist-info/top_level.txt
pyxag-0.0.3.dist-info/RECORD
