Metadata-Version: 2.1
Name: pyxag
Version: 0.0.3
Summary: Hobby research
Home-page: https://github.com/daviddoret/pyxag/wiki
Author: David Doret
Author-email: david.doret@me.com
License: UNKNOWN
Platform: UNKNOWN
Classifier: Programming Language :: Python :: 3
Classifier: License :: OSI Approved :: MIT License
Classifier: Operating System :: OS Independent
Requires-Python: >=3.6
